torchplus/__init__.py
torchplus/version.py
torchplus/data/__init__.py
torchplus/data/data.py
torchplus/datasets/__init__.py
torchplus/datasets/folder.py
torchplus/datasets/ksdd.py
torchplus/datasets/ksdd2.py
torchplus/distributed/__init__.py
torchplus/distributed/federated.py
torchplus/math/__init__.py
torchplus/models/__init__.py
torchplus/models/resnet.py
torchplus/models/vgg.py
torchplus/nn/__init__.py
torchplus/nn/functional.py
torchplus/nn/loss.py
torchplus/nn/poweramp.py
torchplus/transforms/__init__.py
torchplus/transforms/transforms.py
torchplus/utils/__init__.py
torchplus/utils/accuracy.py
torchplus/utils/init.py
torchplus/utils/utils.py
tplus-0.1.9.4.dist-info/LICENSE
tplus-0.1.9.4.dist-info/METADATA
tplus-0.1.9.4.dist-info/WHEEL
tplus-0.1.9.4.dist-info/top_level.txt
tplus-0.1.9.4.dist-info/RECORD
