Metadata-Version: 2.2
Name: tplus
Version: 0.1.9.4
Summary: Torchplus is a utilities library that extends pytorch and torchvision
Home-page: https://github.com/zhangzp9970/torchplus
Author: Zeping Zhang
Author-email: zhangzp9970@outlook.com
License: GPL-v3
Requires-Python: >=3.8
License-File: LICENSE
Requires-Dist: torch
Requires-Dist: torchvision
Requires-Dist: pillow
Requires-Dist: pandas
Requires-Dist: tensorboard
Dynamic: author
Dynamic: author-email
Dynamic: home-page
Dynamic: license
Dynamic: requires-dist
Dynamic: requires-python
Dynamic: summary
